weapon_selector/__init__.py
weapon_selector/app.py
weapon_selector-0.1.1.dist-info/METADATA
weapon_selector-0.1.1.dist-info/WHEEL
weapon_selector-0.1.1.dist-info/entry_points.txt
weapon_selector-0.1.1.dist-info/top_level.txt
weapon_selector-0.1.1.dist-info/RECORD
