Metadata-Version: 2.1
Name: weapon-selector
Version: 0.1.1
Summary: A simple Splatoon weapon selector assistant
Home-page: https://github.com/AkihiroKakitani/splaWeapon.git
Author: kakitaniakihiro
Author-email: s2222010@stu.musashino-u.ac.jp
License: UNKNOWN
Platform: UNKNOWN
Classifier: Programming Language :: Python :: 3
Classifier: License :: OSI Approved :: MIT License
Classifier: Operating System :: OS Independent
Requires-Python: >=3.6
Requires-Dist: tk
